{
    "levelName": "Tangram 1",
    "posTolerance": 0.05000000074505806,
    "rotTolerance": 15.0,
    "goals": [
        {
            "pieceTag": "triangle_big",
            "relPosition": {
                "x": -0.06759978830814362,
                "y": -0.2105763703584671,
                "z": -1.5882836379432775e-8
            },
            "relRotation": {
                "x": -1.455949529827194e-7,
                "y": -1.587773255096181e-7,
                "z": 0.9238799214363098,
                "w": -0.3826828598976135
            }
        },
        {
            "pieceTag": "generic_shape",
            "relPosition": {
                "x": -0.10486383736133576,
                "y": 0.05366958677768707,
                "z": -2.025184464571339e-9
            },
            "relRotation": {
                "x": 4.2148208478920426e-8,
                "y": -8.429703513002096e-8,
                "z": 0.38268259167671206,
                "w": 0.9238800406455994
            }
        },
        {
            "pieceTag": "generic_shape",
            "relPosition": {
                "x": 0.11759171634912491,
                "y": -0.11108671128749848,
                "z": 2.402823895408801e-8
            },
            "relRotation": {
                "x": 8.121773475977534e-8,
                "y": 9.262249989205884e-8,
                "z": -0.7071077227592468,
                "w": 0.7071061134338379
            }
        },
        {
            "pieceTag": "triangle_small",
            "relPosition": {
                "x": -0.11285394430160523,
                "y": 0.1673016995191574,
                "z": 8.928030759136618e-9
            },
            "relRotation": {
                "x": -2.280980027080659e-8,
                "y": -5.506746703076715e-8,
                "z": 1.0000001192092896,
                "w": -3.598956368477957e-7
            }
        },
        {
            "pieceTag": "triangle_big",
            "relPosition": {
                "x": 0.061118289828300479,
                "y": -0.21704624593257905,
                "z": 0.000004885935140919173
            },
            "relRotation": {
                "x": 7.4536956162774e-8,
                "y": -1.3855876446200455e-9,
                "z": -0.7070929408073425,
                "w": 0.7071208953857422
            }
        },
        {
            "pieceTag": "triangle_small",
            "relPosition": {
                "x": 0.09652011096477509,
                "y": -0.017889995127916337,
                "z": 3.815000582108041e-8
            },
            "relRotation": {
                "x": -2.4709265744604638e-7,
                "y": 3.6107664413975728e-7,
                "z": -0.9238802790641785,
                "w": 0.3826819658279419
            }
        }
    ]
}